casq/__init__.py
casq/bmaExport.py
casq/celldesigner2qual.py
casq/readCD.py
casq/readSBGN.py
casq/simplify.py
casq/utils.py
casq/write.py
casq-1.4.3.dist-info/METADATA
casq-1.4.3.dist-info/WHEEL
casq-1.4.3.dist-info/entry_points.txt
casq-1.4.3.dist-info/licenses/LICENSE
casq-1.4.3.dist-info/RECORD
