Metadata-Version: 2.4
Name: casq
Version: 1.4.3
Summary: CaSQ: Celldesigner as Sbml-Qual
Project-URL: Code, https://gitlab.inria.fr/soliman/casq/
Project-URL: Documentation, https://casq.readthedocs.io/en/latest/
Project-URL: Homepage, https://soliman.gitlabpages.inria.fr/casq/
Project-URL: Mirror, https://github.com/soli/casq
Author-email: Sylvain Soliman <Sylvain.Soliman@inria.fr>
License-Expression: GPL-3.0-or-later
License-File: LICENSE
Classifier: Development Status :: 5 - Production/Stable
Classifier: License :: OSI Approved :: GNU General Public License v3 (GPLv3)
Classifier: Operating System :: OS Independent
Classifier: Programming Language :: Python :: 3
Classifier: Programming Language :: Python :: 3.10
Classifier: Programming Language :: Python :: 3.11
Classifier: Programming Language :: Python :: 3.12
Classifier: Programming Language :: Python :: 3.13
Classifier: Programming Language :: Python :: 3.14
Requires-Python: >=3.7
Requires-Dist: loguru>=0.2.5
Requires-Dist: networkx>=2.2
Provides-Extra: dev
Requires-Dist: ruff>=0.0.289; extra == 'dev'
Provides-Extra: docs
Requires-Dist: sphinx; extra == 'docs'
Requires-Dist: sphinxcontrib-programoutput; extra == 'docs'
